grub/__init__.py
grub/base.py
grub/pycode.py
grub/examples/__init__.py
grub/examples/py_object_docs.py
grub/examples/pypi.py
grub-0.1.4.dist-info/LICENSE
grub-0.1.4.dist-info/METADATA
grub-0.1.4.dist-info/WHEEL
grub-0.1.4.dist-info/top_level.txt
grub-0.1.4.dist-info/RECORD
