Metadata-Version: 2.1
Name: grub
Version: 0.1.4
Summary: A ridiculously simple search engine factory
Home-page: https://github.com/thorwhalen/grub
Author: Thor Whalen
License: apache-2.0
Keywords: search,text mining,natural language processing,search engine
Platform: any
License-File: LICENSE
Requires-Dist: py2store
Requires-Dist: scikit-learn
